setup.py
src/buildbot_junit/__init__.py
src/buildbot_junit/junit.py
src/buildbot_junit.egg-info/PKG-INFO
src/buildbot_junit.egg-info/SOURCES.txt
src/buildbot_junit.egg-info/dependency_links.txt
src/buildbot_junit.egg-info/not-zip-safe
src/buildbot_junit.egg-info/requires.txt
src/buildbot_junit.egg-info/top_level.txt