Metadata-Version: 1.0
Name: buildbot-junit
Version: 0.1
Summary: Junit for buildbot
Home-page: https://github.com/ZeeeL/buildbot-junit
Author: Andrey Stolbuhin
Author-email: an.stol99@gmail.com
License: UNKNOWN
Keywords: buildbot xunit junit steps shellcommand
Platform: UNKNOWN
